cpppo_positioner/__init__.py
cpppo_positioner/__main__.py
cpppo_positioner/main.py
cpppo_positioner/simulator.py
cpppo_positioner/smc.py
cpppo_positioner/smc_test.py
cpppo_positioner/ttyV-setup.py
cpppo_positioner/version.py
cpppo_positioner-3.2.0.dist-info/COPYING
cpppo_positioner-3.2.0.dist-info/LICENSE
cpppo_positioner-3.2.0.dist-info/METADATA
cpppo_positioner-3.2.0.dist-info/WHEEL
cpppo_positioner-3.2.0.dist-info/entry_points.txt
cpppo_positioner-3.2.0.dist-info/top_level.txt
cpppo_positioner-3.2.0.dist-info/RECORD
